PyMEMENTO/__init__.py
PyMEMENTO/_version.py
PyMEMENTO/gmx_util.py
PyMEMENTO/mc_path_sampling.py
PyMEMENTO/modeller_util.py
PyMEMENTO/pdb_util.py
PyMEMENTO/plumed_util.py
PyMEMENTO/pymemento.py
PyMEMENTO/data/README.md
PyMEMENTO/data/termini_ref.pdb
PyMEMENTO/data/termini_ref_proline.pdb
PyMEMENTO/data/amber14sb.ff/Makefile.am
PyMEMENTO/data/amber14sb.ff/Makefile.in
PyMEMENTO/data/amber14sb.ff/aminoacids.arn
PyMEMENTO/data/amber14sb.ff/aminoacids.c.tdb
PyMEMENTO/data/amber14sb.ff/aminoacids.hdb
PyMEMENTO/data/amber14sb.ff/aminoacids.n.tdb
PyMEMENTO/data/amber14sb.ff/aminoacids.r2b
PyMEMENTO/data/amber14sb.ff/aminoacids.rtp
PyMEMENTO/data/amber14sb.ff/aminoacids.vsd
PyMEMENTO/data/amber14sb.ff/atomtypes.atp
PyMEMENTO/data/amber14sb.ff/dna.arn
PyMEMENTO/data/amber14sb.ff/dna.hdb
PyMEMENTO/data/amber14sb.ff/dna.r2b
PyMEMENTO/data/amber14sb.ff/dna.rtp
PyMEMENTO/data/amber14sb.ff/ffbonded.itp
PyMEMENTO/data/amber14sb.ff/ffnonbonded.itp
PyMEMENTO/data/amber14sb.ff/forcefield.doc
PyMEMENTO/data/amber14sb.ff/forcefield.itp
PyMEMENTO/data/amber14sb.ff/gbsa.itp
PyMEMENTO/data/amber14sb.ff/ions.itp
PyMEMENTO/data/amber14sb.ff/rna.arn
PyMEMENTO/data/amber14sb.ff/rna.hdb
PyMEMENTO/data/amber14sb.ff/rna.r2b
PyMEMENTO/data/amber14sb.ff/rna.rtp
PyMEMENTO/data/amber14sb.ff/spc.itp
PyMEMENTO/data/amber14sb.ff/spce.itp
PyMEMENTO/data/amber14sb.ff/tip3p.itp
PyMEMENTO/data/amber14sb.ff/tip4p.itp
PyMEMENTO/data/amber14sb.ff/tip4pew.itp
PyMEMENTO/data/amber14sb.ff/tip5p.itp
PyMEMENTO/data/amber14sb.ff/urea.itp
PyMEMENTO/data/amber14sb.ff/watermodels.dat
PyMEMENTO/data/charmm36-jul2021.ff/aminoacids.arn
PyMEMENTO/data/charmm36-jul2021.ff/aminoacids.c.tdb
PyMEMENTO/data/charmm36-jul2021.ff/aminoacids.hdb
PyMEMENTO/data/charmm36-jul2021.ff/aminoacids.n.tdb
PyMEMENTO/data/charmm36-jul2021.ff/aminoacids.r2b
PyMEMENTO/data/charmm36-jul2021.ff/aminoacids.rtp
PyMEMENTO/data/charmm36-jul2021.ff/atomtypes.atp
PyMEMENTO/data/charmm36-jul2021.ff/carb.c.tdb
PyMEMENTO/data/charmm36-jul2021.ff/carb.hdb
PyMEMENTO-0.1.1.dist-info/LICENSE
PyMEMENTO-0.1.1.dist-info/METADATA
PyMEMENTO-0.1.1.dist-info/WHEEL
PyMEMENTO-0.1.1.dist-info/top_level.txt
PyMEMENTO-0.1.1.dist-info/RECORD
