Metadata-Version: 2.1
Name: PyMEMENTO
Version: 0.1.1
Summary: PyMEMENTO
Author: Simon Lichtinger
Author-email: simon.lichtinger@sjc.ox.ac.uk
License: LGPLv3
Platform: Linux
Requires-Python: >=3.6
License-File: LICENSE
Requires-Dist: MDAnalysis (>=2.0.0)
Requires-Dist: numpy
Requires-Dist: pandas (>=1.1.3)
Requires-Dist: pytest-cov (==3.0.0)
Requires-Dist: GromacsWrapper
